{
  "schemaVersion": 1,
  "id": "stardewhud",
  "version": "1.0.0",
  "name": "StardewHUD",
  "description": "一个星露谷物语风格的HUD模组，显示时间、天气、运势和物品计数器",
  "authors": ["Weatheraintbad"],
  "contact": {
    "sources": "https://github.com/Weatheraintbad/stardewhud"
  },
  "license": "MIT",
  "icon": "assets/stardewhud/icon.png",
  "environment": "client",
  "entrypoints": {
    "client": [
      "wb.stardewhud.StardewHUD"
    ],
    "modmenu": [
      "wb.stardewhud.config.ModMenuIntegration"
    ]
  },
  "mixins": [
    "stardewhud.mixins.json"
  ],
  "depends": {
    "fabricloader": ">=0.16.14",
    "fabric-api": "*",
    "minecraft": "~1.20.1",
    "java": ">=17"
  },
  "custom": {
    "modmenu": {
      "links": {
      }
    }
  }
}